pygoogling/__init__.py
pygoogling/googling.py
pygoogling-0.0.2.dist-info/DESCRIPTION.rst
pygoogling-0.0.2.dist-info/METADATA
pygoogling-0.0.2.dist-info/RECORD
pygoogling-0.0.2.dist-info/WHEEL
pygoogling-0.0.2.dist-info/metadata.json
pygoogling-0.0.2.dist-info/top_level.txt
