Metadata-Version: 1.1
Name: pygoogling
Version: 0.0.2
Summary: Python library to do google search
Home-page: https://github.com/essanpupil/pygoogling
Author: Ikhsan Noor Rosyidin
Author-email: jakethitam1985@gmail.com
License: MIT
Keywords: google search python module
Platform: UNKNOWN
Classifier: Development Status :: 3 - Alpha
Classifier: Intended Audience :: Developers
Classifier: Topic :: Software Development :: Libraries :: Python Modules
Classifier: License :: OSI Approved :: MIT License
Classifier: Programming Language :: Python :: 2.7
Classifier: Programming Language :: Python :: 3.4
